<!-- edited with XMLSPY v5 rel. 2 U (http://www.xmlspy.com) by Robert Nicaise (Big Huge Games) -->
<!-- LOCALIZATION: LEADER and CITY elements; also, name attribute -->
<TRIBE name="Iroquois">
  <LEADERS>
    <LEADER>Hiawatha</LEADER>
    <LEADER>Deganawida </LEADER>
    <LEADER>Donehogawa</LEADER>
  </LEADERS>
  <CITIES>
    <CITY>Chondote</CITY>
    <CITY>Gewauga</CITY>
    <CITY>Canajoharie</CITY>
    <CITY>Cattaraugus</CITY>
    <CITY>Schaunactada </CITY>
    <CITY>Schoharie</CITY>
    <CITY>Chittenango</CITY>
    <CITY>Tuscarora</CITY>
    <CITY>Onondaga</CITY>
    <CITY>Kashong </CITY>
    <CITY>Chemung</CITY>
    <CITY>Jennesedaga </CITY>
    <CITY>Ganogeh</CITY>
    <CITY>Kawauka</CITY>
    <CITY>Owego</CITY>
    <CITY>Nowadaga</CITY>
    <CITY>Saratoga</CITY>
    <CITY>Chittenango</CITY>
    <CITY>Ossewingo</CITY>
    <CITY>Ahaouet</CITY>
    <CITY>Touenho</CITY>
    <CITY>Shawiangto</CITY>
    <CITY>Gahato</CITY>
    <CITY>Onnahee</CITY>
    <CITY>Gandasetaigon</CITY>
    <CITY>Kente</CITY>
    <CITY>Kiohero</CITY>
    <CITY>Neodakhent</CITY>
    <CITY>Oneniole</CITY>
    <CITY>Skannayutenate</CITY>
  </CITIES>
  <UNIT_CONTINENT>2 American</UNIT_CONTINENT>
  <BUILD_CONTINENT>4 American</BUILD_CONTINENT>
</TRIBE>
